{
  "project_info": {
    "project_number": "1014578566637",
    "project_id": "godavaii",
    "storage_bucket": "godavaii.firebasestorage.app"
  },
  "client": [
    {
      "client_info": {
        "mobilesdk_app_id": "1:1014578566637:android:8ec4675296a6c8026e03e4",
        "android_client_info": {
          "package_name": "com.godavaii.app"
        }
      },
      "oauth_client": [],
      "api_key": [
        {
          "current_key": "AIzaSyAzr-do-njkkj8f6BAtb6NuWxvqT7zF2lU"
        }
      ],
      "services": {
        "appinvite_service": {
          "other_platform_oauth_client": []
        }
      }
    }
  ],
  "configuration_version": "1"
}